MANIFEST.in
README.rst
gramme.py
setup.py
gramme.egg-info/PKG-INFO
gramme.egg-info/SOURCES.txt
gramme.egg-info/dependency_links.txt
gramme.egg-info/requires.txt
gramme.egg-info/top_level.txt
gramme.egg-info/zip-safe